subwhisper/__init__.py
subwhisper/transcribe.py
subwhisper-0.1.1.dist-info/METADATA
subwhisper-0.1.1.dist-info/WHEEL
subwhisper-0.1.1.dist-info/RECORD
