Metadata-Version: 2.1
Name: subwhisper
Version: 0.1.1
Summary: 
Author: tupiznak
Author-email: akej-vonavi@mail.ru
Requires-Python: >=3.10,<4.0
Classifier: Programming Language :: Python :: 3
Classifier: Programming Language :: Python :: 3.10
Classifier: Programming Language :: Python :: 3.11
